ema_pytorch/__init__.py
ema_pytorch/ema_pytorch.py
ema_pytorch/ema_pytree_pytorch.py
ema_pytorch/post_hoc_ema.py
ema_pytorch-0.7.8.dist-info/licenses/LICENSE
ema_pytorch-0.7.8.dist-info/METADATA
ema_pytorch-0.7.8.dist-info/WHEEL
ema_pytorch-0.7.8.dist-info/top_level.txt
ema_pytorch-0.7.8.dist-info/RECORD
